README.rst
setup.py
bin/cartodb_backup
cartodb_backup/__init__.py
cartodb_backup/cartodb_backup.py
cartodb_backup/cli.py
cartodb_backup.egg-info/PKG-INFO
cartodb_backup.egg-info/SOURCES.txt
cartodb_backup.egg-info/dependency_links.txt
cartodb_backup.egg-info/requires.txt
cartodb_backup.egg-info/top_level.txt