Metadata-Version: 1.1
Name: cartodb-backup
Version: 0.1
Summary: Python CLI to make a backup of an entire CartoDB domain to SQL dump file (zipped). Optionally you can restore SQL dumped file to a new (created) PostGIS DB. Also you can upload sql files to Amazon S3.
Home-page: http://github.com/GeographicaGS/CartoDB_Backup
Author: Cayetano Benavent
Author-email: cayetano.benavent@geographica.gs
License: GPLv2
Keywords: cartodb GIS postgis
Platform: UNKNOWN
Classifier: Development Status :: 4 - Beta
Classifier: Intended Audience :: Developers
Classifier: License :: OSI Approved :: GNU General Public License v2 (GPLv2)
Classifier: Programming Language :: Python :: 2.7
Classifier: Operating System :: OS Independent
Classifier: Topic :: Scientific/Engineering :: GIS
